<?xml version="1.0" encoding="utf-8" ?><dwsync><file name="blog-10.php" server="ssh.phx.nearlyfreespeech.net" local="3559211585" remote="3559211588" Dst="-1" /><file name="blog-3.php" server="ssh.phx.nearlyfreespeech.net" local="3559211005" remote="3559211014" Dst="-1" /><file name="blog-4.php" server="ssh.phx.nearlyfreespeech.net" local="3559211154" remote="3559211158" Dst="-1" /><file name="blog-5.php" server="ssh.phx.nearlyfreespeech.net" local="3559211295" remote="3559211298" Dst="-1" /><file name="blog-2.php" server="ssh.phx.nearlyfreespeech.net" local="3559171343" remote="3559171347" Dst="-1" /><file name="blog-11.php" server="ssh.phx.nearlyfreespeech.net" local="3559211639" remote="3559211642" Dst="-1" /><file name="blog-1.php" server="ssh.phx.nearlyfreespeech.net" local="3559229549" remote="3559229554" Dst="-1" /><file name="blog-6.php" server="ssh.phx.nearlyfreespeech.net" local="3559211352" remote="3559211354" Dst="-1" /><file name="blog-8.php" server="ssh.phx.nearlyfreespeech.net" local="3559211464" remote="3559211469" Dst="-1" /><file name="blog-12.php" server="ssh.phx.nearlyfreespeech.net" local="3559211709" remote="3559211713" Dst="-1" /><file name=".DS_Store" server="ssh.phx.nearlyfreespeech.net" local="3541617166" remote="3541617166" Dst="-1" /><file name="blog-9.php" server="ssh.phx.nearlyfreespeech.net" local="3559211527" remote="3559211530" Dst="-1" /><file name="blog-7.php" server="ssh.phx.nearlyfreespeech.net" local="3559211406" remote="3559211410" Dst="-1" /><file name="blog-13.php" server="ssh.phx.nearlyfreespeech.net" local="3559211762" remote="3559211765" Dst="-1" /><file name="gallery.php" server="ssh.phx.nearlyfreespeech.net" local="3559073480" remote="3559073480" Dst="-1" /><file name="test.php" server="ssh.phx.nearlyfreespeech.net" local="3559256011" remote="3559256048" Dst="-1" /><file name="blog-10_no_min.php" server="ssh.phx.nearlyfreespeech.net" local="3559211568" remote="3559223430" Dst="-1" /><file name="blog-11_no_min.php" server="ssh.phx.nearlyfreespeech.net" local="3559211622" remote="3559223433" Dst="-1" /><file name="blog-12_no_min.php" server="ssh.phx.nearlyfreespeech.net" local="3559211674" remote="3559223436" Dst="-1" /><file name="blog-13_no_min.php" server="ssh.phx.nearlyfreespeech.net" local="3559211745" remote="3559223439" Dst="-1" /><file name="blog-1_no_min.php" server="ssh.phx.nearlyfreespeech.net" local="3559169700" remote="3559223440" Dst="-1" /><file name="blog-2_no_min.php" server="ssh.phx.nearlyfreespeech.net" local="3559171306" remote="3559223443" Dst="-1" /><file name="blog-3_no_min.php" server="ssh.phx.nearlyfreespeech.net" local="3559210978" remote="3559223444" Dst="-1" /><file name="blog-4_no_min.php" server="ssh.phx.nearlyfreespeech.net" local="3559211119" remote="3559223447" Dst="-1" /><file name="blog-5_no_min.php" server="ssh.phx.nearlyfreespeech.net" local="3559211277" remote="3559223448" Dst="-1" /><file name="blog-6_no_min.php" server="ssh.phx.nearlyfreespeech.net" local="3559211333" remote="3559223448" Dst="-1" /><file name="blog-7_no_min.php" server="ssh.phx.nearlyfreespeech.net" local="3559211388" remote="3559223452" Dst="-1" /><file name="blog-8_no_min.php" server="ssh.phx.nearlyfreespeech.net" local="3559211445" remote="3559223452" Dst="-1" /><file name="blog-9_no_min.php" server="ssh.phx.nearlyfreespeech.net" local="3559211508" remote="3559223455" Dst="-1" /><file name="gallery_no_min.php" server="ssh.phx.nearlyfreespeech.net" local="3558621856" remote="3559223459" Dst="-1" /><file name="blog-14_no_min.php" server="ssh.phx.nearlyfreespeech.net" local="3559474932" remote="3559475041" Dst="-1" /><file name="blog-14.php" server="ssh.phx.nearlyfreespeech.net" local="3559505393" remote="3559505397" Dst="-1" /></dwsync>